nano_banana_pro_prompt/__init__.py
nano_banana_pro_prompt-1768559.175.715.dist-info/licenses/LICENSE
nano_banana_pro_prompt-1768559.175.715.dist-info/METADATA
nano_banana_pro_prompt-1768559.175.715.dist-info/WHEEL
nano_banana_pro_prompt-1768559.175.715.dist-info/top_level.txt
nano_banana_pro_prompt-1768559.175.715.dist-info/RECORD
