Metadata-Version: 2.4
Name: nano-banana-pro-prompt
Version: 1768559.175.715
Summary: High-quality integration for https://supermaker.ai/blog/nano-banana-pro-prompt-use-cases-ready-to-copy-paste/
Home-page: https://supermaker.ai/blog/nano-banana-pro-prompt-use-cases-ready-to-copy-paste/
Author: SuperMaker
Classifier: Programming Language :: Python :: 3
Classifier: License :: OSI Approved :: MIT License
Requires-Python: >=3.6
License-File: LICENSE
Dynamic: author
Dynamic: classifier
Dynamic: description
Dynamic: description-content-type
Dynamic: home-page
Dynamic: license-file
Dynamic: requires-python
Dynamic: summary
